{
	"id" : "DMII_protocol_20120830",
	"type" : "protocol_definition",
	"selfLink": "/frame/info/DMII_protocol_20120830",
	"name" : "DM II",
	"icdCode": "urn:icd:250.00",
	"conditionType": "Chronic Conditions",
	"status": "<span style=\"color: red; font-weight: bold;\">Screening Due</span>",
	"class" : "gov.va.cpe.vpr.frameeng.ProtocolFrame",
	"viewdef" : "gov.va.cpe.vpr.queryeng.DiabetesViewDef",
	"med_filters": {"qfilter_status": "ACTIVE,PENDING", "filter_class_code": "urn:vadc:HS502,urn:vadc:BL110"},  
    "relevantDrugClasses": {
    	"urn:vadc:HS502": "Oral Hypoglycemics",
    	"urn:vadc:BL110": "ANTICOAGULANTS"
    },
	"links": {
		"VA Clinical Pracice Guideline: DM in Primary Care (2010)": "http://www.healthquality.domain/Diabetes_Mellitus.asp",
		"UpToDate: Diabetes melitus": "http://www.uptodate.com/contents/search?search=diabetes+mellitus&sp=0&searchType=PLAIN_TEXT&source=USER_INPUT&searchControl=TOP_PULLDOWN&searchOffset=&autoComplete=true"
	},
	"relevantLabs" : [
		"AgbA1c",
		"serum glocose"
	],
	"candidates": [
		{
			"desc": "Fasting plasma glucose level ≥ 7.0 mmol/l (126 mg/dl)",
			"trigger": {
				"class": "gov.va.cpe.vpr.frameeng.IFrameTrigger.LabResultRangeTrigger",
				"params": [
					"GLUCOSE",
					7.0 
				]
			}
		},{
			"desc": "Glycated hemoglobin (Hb A1C) ≥ 6.5%",
			"trigger": {
				"class": "gov.va.cpe.vpr.frameeng.IFrameTrigger.LabResultRangeTrigger",
				"params": [
					"HEMOGLOBIN A1C",
					6.5
				]
			}
		}
	],
	"goals" : {
		"height_obs" : {
			"name" : "Height",
			"guideline" : "21+yo: once after age 21",
			"type" : "obs_frequency",
			"type_interval" : "1y",
			"trigger" : {
				"class" : "gov.va.cpe.vpr.frameeng.IFrameTrigger.NewVitalSignTrigger",
				"params" : [
					"HEIGHT"
				]
			},
			"query" : "/vpr/{pid}/latest/vs-time?range=HEIGHT"
		}
	}
}
